snakyscraper/__init__.py
snakyscraper-1.0.0.dist-info/licenses/LICENSE
snakyscraper-1.0.0.dist-info/METADATA
snakyscraper-1.0.0.dist-info/WHEEL
snakyscraper-1.0.0.dist-info/top_level.txt
snakyscraper-1.0.0.dist-info/RECORD
