Metadata-Version: 2.4
Name: snakyscraper
Version: 1.0.0
Summary: SnakyScraper is a lightweight and Pythonic web scraping toolkit built on top of BeautifulSoup and Requests. It provides an elegant interface for extracting structured HTML and metadata from websites with clean, direct outputs.
Home-page: https://github.com/riodevnet/snakyscraper
Author: Rio Dev
Author-email: my.riodev.net@gmail.com
License: MIT
Keywords: snakyscraper,scraping,scraper
Classifier: Development Status :: 3 - Alpha
Classifier: Intended Audience :: Developers
Classifier: Topic :: Software Development :: Build Tools
Classifier: License :: OSI Approved :: MIT License
Classifier: Programming Language :: Python :: 3
Classifier: Programming Language :: Python :: 3.6
Classifier: Programming Language :: Python :: 3.7
Classifier: Programming Language :: Python :: 3.8
Classifier: Programming Language :: Python :: 3.9
Classifier: Programming Language :: Python :: 3.10
Classifier: Programming Language :: Python :: 3.11
Classifier: Programming Language :: Python :: 3.12
Classifier: Programming Language :: Python :: 3.13
Classifier: Programming Language :: Python :: 3.14
Requires-Python: >=3.6
License-File: LICENSE
Requires-Dist: requests
Requires-Dist: beautifulsoup4
Requires-Dist: lxml
Dynamic: author
Dynamic: author-email
Dynamic: classifier
Dynamic: description
Dynamic: description-content-type
Dynamic: home-page
Dynamic: keywords
Dynamic: license
Dynamic: license-file
Dynamic: requires-dist
Dynamic: requires-python
Dynamic: summary
